qrek-0.0.3.dist-info/METADATA
qrek-0.0.3.dist-info/WHEEL
qrek/__init__.py
qrek/qrek.abi3.so
qrek-0.0.3.dist-info/RECORD
