Metadata-Version: 2.4
Name: qrek
Version: 0.0.3
Classifier: Development Status :: 3 - Alpha
Classifier: Intended Audience :: Developers
Classifier: License :: OSI Approved :: MIT License
Classifier: License :: OSI Approved :: Apache Software License
Classifier: Programming Language :: Python :: 3
Classifier: Programming Language :: Python :: 3.8
Classifier: Programming Language :: Python :: 3.9
Classifier: Programming Language :: Python :: 3.10
Classifier: Programming Language :: Python :: 3.11
Classifier: Programming Language :: Python :: 3.12
Classifier: Programming Language :: Rust
Classifier: Topic :: Security :: Cryptography
Summary: Quantum-Resilient Encryption Kit - Python SDK
Keywords: cryptography,quantum,encryption,security,entropy
Author: qREK Team
License: MIT OR Apache-2.0
Requires-Python: >=3.8
Project-URL: Homepage, https://github.com/qsegroup/qREK
Project-URL: Repository, https://github.com/qsegroup/qREK
Project-URL: Documentation, https://github.com/qsegroup/qREK/tree/main/docs
